Metadata-Version: 2.1
Name: geosmapdemo
Version: 0.0.1
Summary: this is a software for interactive mapping. 
Home-page: https://github.com/zyang91/geosmapdemo
Author: Zhanchao Yang
Author-email: zyang91@binghamton.edu
License: MIT license
Keywords: geosmapdemo
Classifier: Development Status :: 2 - Pre-Alpha
Classifier: Intended Audience :: Developers
Classifier: License :: OSI Approved :: MIT License
Classifier: Natural Language :: English
Classifier: Programming Language :: Python :: 3
Classifier: Programming Language :: Python :: 3.7
Classifier: Programming Language :: Python :: 3.8
Classifier: Programming Language :: Python :: 3.9
Classifier: Programming Language :: Python :: 3.10
Requires-Python: >=3.7
License-File: LICENSE
